plastinet/__init__.py
plastinet/analysis/__init__.py
plastinet/analysis/attention_analysis.py
plastinet/analysis/expression_analysis.py
plastinet/analysis/pseudotime.py
plastinet/analysis/spatial_colocalization.py
plastinet/data/__init__.py
plastinet/data/data_loader.py
plastinet/data/graph_utils.py
plastinet/models/__init__.py
plastinet/models/attention.py
plastinet/models/plastinet_model.py
plastinet/visualization/__init__.py
plastinet/visualization/plots.py
plastinet/visualization/pseudotime_plots.py
plastinet-0.1.9.dist-info/METADATA
plastinet-0.1.9.dist-info/WHEEL
plastinet-0.1.9.dist-info/top_level.txt
plastinet-0.1.9.dist-info/RECORD
